{
	"info": {
		"_postman_id": "b4cf133e-b880-4fab-b1f8-52b2f976156d",
		"name": "Hotelin-app API",
		"schema": "https://schema.getpostman.com/json/collection/v2.1.0/collection.json"
	},
	"item": [
		{
			"name": "User",
			"item": [
				{
					"name": "Create User",
					"request": {
						"method": "POST",
						"header": [],
						"body": {
							"mode": "raw",
							"raw": "{\n  \"email\": \"{{$randomExampleEmail}}\",\n  \"firstName\": \"{{$randomFirstName}}\",\n  \"lastName\": \"{{$randomLastName}}\",\n  \"password\": \"password1\",\n  \"role\": \"user\"\n}",
							"options": {
								"raw": {
									"language": "json"
								}
							}
						},
						"url": {
							"raw": "http://localhost:3000/v1/users/",
							"protocol": "http",
							"host": [
								"localhost"
							],
							"port": "3000",
							"path": [
								"v1",
								"users",
								""
							]
						}
					},
					"response": []
				},
				{
					"name": "Get User",
					"request": {
						"method": "GET",
						"header": [],
						"url": {
							"raw": "http://localhost:3000/v1/users/1",
							"protocol": "http",
							"host": [
								"localhost"
							],
							"port": "3000",
							"path": [
								"v1",
								"users",
								"1"
							]
						}
					},
					"response": []
				},
				{
					"name": "Get All Users",
					"request": {
						"method": "GET",
						"header": [],
						"url": {
							"raw": "http://localhost:3000/v1/users/",
							"protocol": "http",
							"host": [
								"localhost"
							],
							"port": "3000",
							"path": [
								"v1",
								"users",
								""
							]
						}
					},
					"response": []
				},
				{
					"name": "Update User",
					"request": {
						"method": "PATCH",
						"header": [],
						"body": {
							"mode": "raw",
							"raw": "{\n  \"email\": \"{{$randomExampleEmail}}\",\n  \"firstName\": \"{{$randomFirstName}}\",\n  \"lastName\": \"{{$randomLastName}}\"\n}",
							"options": {
								"raw": {
									"language": "json"
								}
							}
						},
						"url": {
							"raw": "http://localhost:3000/v1/users/3",
							"protocol": "http",
							"host": [
								"localhost"
							],
							"port": "3000",
							"path": [
								"v1",
								"users",
								"3"
							],
							"query": [
								{
									"key": "",
									"value": null,
									"disabled": true
								}
							]
						}
					},
					"response": []
				},
				{
					"name": "Delete User",
					"request": {
						"method": "DELETE",
						"header": [],
						"url": {
							"raw": "http://localhost:3000/v1/users/1",
							"protocol": "http",
							"host": [
								"localhost"
							],
							"port": "3000",
							"path": [
								"v1",
								"users",
								"1"
							]
						}
					},
					"response": []
				},
				{
					"name": "Get User Reservations",
					"request": {
						"method": "GET",
						"header": [],
						"url": {
							"raw": "http://localhost:3000/v1/users/1/reservations",
							"protocol": "http",
							"host": [
								"localhost"
							],
							"port": "3000",
							"path": [
								"v1",
								"users",
								"1",
								"reservations"
							]
						}
					},
					"response": []
				}
			]
		},
		{
			"name": "Auth",
			"item": [
				{
					"name": "Register",
					"request": {
						"method": "POST",
						"header": [],
						"body": {
							"mode": "raw",
							"raw": "{\n    \"email\": \"clyde_felix@email.com\",\n    \"firstName\": \"Clyde James\",\n    \"lastName\": \"Felix\",\n    \"password\": \"password1\"\n}",
							"options": {
								"raw": {
									"language": "json"
								}
							}
						},
						"url": {
							"raw": "http://localhost:3000/v1/auth/register",
							"protocol": "http",
							"host": [
								"localhost"
							],
							"port": "3000",
							"path": [
								"v1",
								"auth",
								"register"
							]
						}
					},
					"response": []
				},
				{
					"name": "Register (random)",
					"request": {
						"method": "POST",
						"header": [],
						"body": {
							"mode": "raw",
							"raw": "{\n    \"email\": \"{{$randomExampleEmail}}\",\n    \"firstName\": \"{{$randomFirstName}}\",\n    \"lastName\": \"{{$randomLastName}}\",\n    \"password\": \"password1\"\n}",
							"options": {
								"raw": {
									"language": "json"
								}
							}
						},
						"url": {
							"raw": "http://localhost:3000/v1/auth/register",
							"protocol": "http",
							"host": [
								"localhost"
							],
							"port": "3000",
							"path": [
								"v1",
								"auth",
								"register"
							]
						}
					},
					"response": []
				},
				{
					"name": "Login",
					"event": [
						{
							"listen": "test",
							"script": {
								"exec": [
									"if(pm.response.code == 200) {",
									"    pm.environment.set(\"accessToken\", pm.response.json().tokens.access.token);",
									"    pm.environment.set(\"refreshToken\", pm.response.json().tokens.refresh.token);",
									"}"
								],
								"type": "text/javascript"
							}
						}
					],
					"request": {
						"method": "POST",
						"header": [],
						"body": {
							"mode": "raw",
							"raw": "{\n    \"email\": \"clyde_felix@email.com\",\n    \"password\": \"password1\"\n}",
							"options": {
								"raw": {
									"language": "json"
								}
							}
						},
						"url": {
							"raw": "localhost:3000/v1/auth/login",
							"host": [
								"localhost"
							],
							"port": "3000",
							"path": [
								"v1",
								"auth",
								"login"
							]
						}
					},
					"response": []
				},
				{
					"name": "Logout",
					"request": {
						"method": "POST",
						"header": [],
						"body": {
							"mode": "raw",
							"raw": "{\n    \"refreshToken\": \"{{refreshToken}}\"\n}",
							"options": {
								"raw": {
									"language": "json"
								}
							}
						},
						"url": {
							"raw": "http://localhost:3000/v1/auth/logout",
							"protocol": "http",
							"host": [
								"localhost"
							],
							"port": "3000",
							"path": [
								"v1",
								"auth",
								"logout"
							]
						}
					},
					"response": []
				},
				{
					"name": "Refresh Tokens",
					"request": {
						"method": "POST",
						"header": [],
						"body": {
							"mode": "raw",
							"raw": "{\n    \"refreshToken\": \"{{refreshToken}}\"\n}",
							"options": {
								"raw": {
									"language": "json"
								}
							}
						},
						"url": {
							"raw": "http://localhost:3000/v1/auth/refresh-tokens",
							"protocol": "http",
							"host": [
								"localhost"
							],
							"port": "3000",
							"path": [
								"v1",
								"auth",
								"refresh-tokens"
							]
						}
					},
					"response": []
				},
				{
					"name": "Show Info",
					"request": {
						"method": "GET",
						"header": [],
						"url": {
							"raw": "http://localhost:3000/v1/auth/account/1",
							"protocol": "http",
							"host": [
								"localhost"
							],
							"port": "3000",
							"path": [
								"v1",
								"auth",
								"account",
								"1"
							]
						}
					},
					"response": []
				}
			]
		},
		{
			"name": "Reservation",
			"item": [
				{
					"name": "Create Reservation",
					"request": {
						"method": "POST",
						"header": [],
						"body": {
							"mode": "raw",
							"raw": "{\n    \"userId\": 2,\n    \"workspaceId\": 2,\n    \"startDate\": \"2021/07/21\",\n    \"endDate\": \"2021/07/21\"\n}",
							"options": {
								"raw": {
									"language": "json"
								}
							}
						},
						"url": {
							"raw": "http://localhost:3000/v1/reserve/",
							"protocol": "http",
							"host": [
								"localhost"
							],
							"port": "3000",
							"path": [
								"v1",
								"reserve",
								""
							]
						}
					},
					"response": []
				},
				{
					"name": "Get Available Workspaces",
					"request": {
						"method": "POST",
						"header": [],
						"body": {
							"mode": "raw",
							"raw": "{\n    \"startDate\": \"2021/07/19\",\n    \"endDate\": \"2021/07/19\"\n    }",
							"options": {
								"raw": {
									"language": "json"
								}
							}
						},
						"url": {
							"raw": "http://localhost:3000/v1/reserve/schedule",
							"protocol": "http",
							"host": [
								"localhost"
							],
							"port": "3000",
							"path": [
								"v1",
								"reserve",
								"schedule"
							]
						}
					},
					"response": []
				},
				{
					"name": "Get Reservation",
					"request": {
						"method": "GET",
						"header": [],
						"url": {
							"raw": "http://localhost:3000/v1/reserve/1",
							"protocol": "http",
							"host": [
								"localhost"
							],
							"port": "3000",
							"path": [
								"v1",
								"reserve",
								"1"
							]
						}
					},
					"response": []
				}
			]
		},
		{
			"name": "Workspace",
			"item": [
				{
					"name": "Create Workspace",
					"request": {
						"method": "POST",
						"header": [],
						"body": {
							"mode": "raw",
							"raw": "{\n    \"description\": \"By the window\"\n}",
							"options": {
								"raw": {
									"language": "json"
								}
							}
						},
						"url": {
							"raw": "http://localhost:3000/v1/workspaces/",
							"protocol": "http",
							"host": [
								"localhost"
							],
							"port": "3000",
							"path": [
								"v1",
								"workspaces",
								""
							]
						}
					},
					"response": []
				},
				{
					"name": "Get Workspace",
					"request": {
						"method": "GET",
						"header": [],
						"url": {
							"raw": "http://localhost:3000/v1/workspaces/1",
							"protocol": "http",
							"host": [
								"localhost"
							],
							"port": "3000",
							"path": [
								"v1",
								"workspaces",
								"1"
							]
						}
					},
					"response": []
				},
				{
					"name": "Get All Workspaces",
					"request": {
						"method": "GET",
						"header": [],
						"url": {
							"raw": "http://localhost:3000/v1/admin/workspaces/",
							"protocol": "http",
							"host": [
								"localhost"
							],
							"port": "3000",
							"path": [
								"v1",
								"admin",
								"workspaces",
								""
							]
						}
					},
					"response": []
				}
			]
		},
		{
			"name": "Admin",
			"item": [
				{
					"name": "Get All Users",
					"request": {
						"method": "GET",
						"header": [],
						"url": {
							"raw": "http://localhost:3000/v1/admin/users",
							"protocol": "http",
							"host": [
								"localhost"
							],
							"port": "3000",
							"path": [
								"v1",
								"admin",
								"users"
							]
						}
					},
					"response": []
				},
				{
					"name": "Get All Workspaces",
					"request": {
						"method": "GET",
						"header": [],
						"url": {
							"raw": "http://localhost:3000/v1/admin/workspaces",
							"protocol": "http",
							"host": [
								"localhost"
							],
							"port": "3000",
							"path": [
								"v1",
								"admin",
								"workspaces"
							]
						}
					},
					"response": []
				},
				{
					"name": "Get All Reservations",
					"request": {
						"method": "GET",
						"header": [],
						"url": {
							"raw": "http://localhost:3000/v1/admin/reservations",
							"protocol": "http",
							"host": [
								"localhost"
							],
							"port": "3000",
							"path": [
								"v1",
								"admin",
								"reservations"
							]
						}
					},
					"response": []
				}
			]
		},
		{
			"name": "Health check",
			"request": {
				"method": "GET",
				"header": [],
				"url": {
					"raw": "http://localhost:3000/health",
					"protocol": "http",
					"host": [
						"localhost"
					],
					"port": "3000",
					"path": [
						"health"
					]
				}
			},
			"response": []
		}
	],
	"auth": {
		"type": "bearer",
		"bearer": [
			{
				"key": "token",
				"value": "{{accessToken}}",
				"type": "string"
			}
		]
	},
	"event": [
		{
			"listen": "prerequest",
			"script": {
				"type": "text/javascript",
				"exec": [
					""
				]
			}
		},
		{
			"listen": "test",
			"script": {
				"type": "text/javascript",
				"exec": [
					""
				]
			}
		}
	]
}